firefly/__init__.py
firefly/_archive.py
firefly/_plot.py
firefly/_utils.py
firefly/auto_retrieval.py
firefly/data/spear.csv
firefly/data/spear_uncoupled.csv
firefly/data/Candidates/13_sector_candidates.csv
firefly/data/Candidates/14_sector_candidates.csv
firefly/data/Candidates/15_sector_candidates.csv
firefly/data/Candidates/16_sector_candidates.csv
firefly/data/Candidates/17_sector_candidates.csv
firefly/data/Candidates/18_sector_candidates.csv
firefly/data/Candidates/19_sector_candidates.csv
firefly/data/Filters/TESS_filter.csv
firefly/data/Search/TESS_lc.csv.xz
firefly/data/Search/TESS_lc_fast.csv.xz
firefly/data/Targets/all_tess_viable.csv
firefly/data/Targets/eu_tess_viable.csv
firefly/data/Targets/nasa_product_list.csv.xz
firefly/data/Targets/nasa_tess_viable.csv
firefly/data/Targets/nasa_tess_viable_fast.csv
firefly/data/Targets/org_tess_viable.csv
firefly/data/Targets/tess_ttv_viable.csv
firefly_tess-0.9.3.dist-info/licenses/LICENSE
firefly_tess-0.9.3.dist-info/METADATA
firefly_tess-0.9.3.dist-info/WHEEL
firefly_tess-0.9.3.dist-info/top_level.txt
firefly_tess-0.9.3.dist-info/RECORD
