Metadata-Version: 2.4
Name: firefly-tess
Version: 0.9.3
Summary: A pipeline to use with TransitFit to fit TESS lightcurves.
Download-URL: https://github.com/sourestdeeds/firefly/archive/refs/tags/v2.0.0.tar.gz
Author: Stephen Charles
Requires-Python: >=3.6
License-File: LICENSE
Requires-Dist: numpy
Requires-Dist: pandas
Requires-Dist: tabulate
Requires-Dist: thefuzz
Requires-Dist: python-Levenshtein
Requires-Dist: natsort
Requires-Dist: seaborn
Requires-Dist: astroquery
Requires-Dist: pyastronomy
Requires-Dist: astropy
Requires-Dist: lightkurve
Requires-Dist: transitfit
Requires-Dist: rich
Requires-Dist: tqdm
Dynamic: author
Dynamic: download-url
Dynamic: license-file
Dynamic: requires-python
